hoopa/__init__.py
hoopa/downloader.py
hoopa/dupefilters.py
hoopa/exceptions.py
hoopa/item.py
hoopa/middleware.py
hoopa/pipelines.py
hoopa/queues.py
hoopa/request.py
hoopa/response.py
hoopa/statscollectors.py
hoopa/commands/__init__.py
hoopa/commands/cmdline.py
hoopa/commands/create.py
hoopa/core/__init__.py
hoopa/core/downloadermiddleware.py
hoopa/core/engine.py
hoopa/core/scheduler.py
hoopa/core/spider.py
hoopa/core/spidermiddleware.py
hoopa/downloadermiddlewares/__init__.py
hoopa/downloadermiddlewares/handle_http_error.py
hoopa/downloadermiddlewares/handle_http_success.py
hoopa/downloadermiddlewares/stats.py
hoopa/pipelinemiddlewares/__init__.py
hoopa/pipelinemiddlewares/default_pipeline.py
hoopa/pipelinemiddlewares/handle_process_error.py
hoopa/settings/__init__.py
hoopa/settings/const.py
hoopa/settings/default_settings.py
hoopa/spidermiddlewares/__init__.py
hoopa/spidermiddlewares/handle_parse_error.py
hoopa/templates/project_spider_template.tmpl
hoopa/templates/spider_full_template.tmpl
hoopa/templates/spider_template.tmpl
hoopa/templates/project_template/config/__init__.py
hoopa/templates/project_template/config/settings.py
hoopa/templates/project_template/items/__init__.py
hoopa/templates/project_template/items/data_item.py
hoopa/templates/project_template/middlewares/__init__.py
hoopa/templates/project_template/middlewares/common_middleware.py
hoopa/utils/__init__.py
hoopa/utils/asynciter.py
hoopa/utils/concurrency.py
hoopa/utils/connection.py
hoopa/utils/decorators.py
hoopa/utils/helpers.py
hoopa/utils/log.py
hoopa/utils/project.py
hoopa/utils/serialization.py
hoopa/utils/url.py
hoopa-0.1.18.dist-info/licenses/LICENSE
hoopa-0.1.18.dist-info/METADATA
hoopa-0.1.18.dist-info/WHEEL
hoopa-0.1.18.dist-info/entry_points.txt
hoopa-0.1.18.dist-info/top_level.txt
hoopa-0.1.18.dist-info/RECORD
