Metadata-Version: 2.4
Name: hoopa
Version: 0.1.18
Summary: Asynchronous crawler micro-framework based on python.
Home-page: https://github.com/fishtn/hoopa
Author: fishtn
Author-email: 
License: MIT
Classifier: Framework :: AsyncIO
Classifier: Intended Audience :: Developers
Classifier: Development Status :: 3 - Alpha
Classifier: License :: OSI Approved :: MIT License
Classifier: Operating System :: POSIX :: Linux
Classifier: Operating System :: MacOS :: MacOS X
Classifier: Operating System :: POSIX :: BSD
Classifier: Operating System :: Microsoft :: Windows
Classifier: Programming Language :: Python :: 3.9
Classifier: Topic :: Internet :: WWW/HTTP
Classifier: Topic :: Software Development :: Libraries :: Application Frameworks
Classifier: Topic :: Software Development :: Libraries :: Python Modules
Requires-Python: >=3.9
License-File: LICENSE
Requires-Dist: aiohttp>=3.9.5
Requires-Dist: httpx[http2]>=0.17.0
Requires-Dist: redis>=4.6.0
Requires-Dist: requests
Requires-Dist: parsel
Requires-Dist: aiodns
Requires-Dist: charset-normalizer
Requires-Dist: arrow
Requires-Dist: w3lib
Requires-Dist: loguru
Requires-Dist: ujson
Requires-Dist: lxml
Provides-Extra: uvloop
Requires-Dist: uvloop; extra == "uvloop"
Dynamic: author
Dynamic: classifier
Dynamic: description
Dynamic: description-content-type
Dynamic: home-page
Dynamic: license
Dynamic: license-file
Dynamic: provides-extra
Dynamic: requires-dist
Dynamic: requires-python
Dynamic: summary
